__init__.py
telus_bulk/__init__.py
telus_bulk/helpers/mutiple_spaces.py
telus_bulk/helpers/cron_job/__init__.py
telus_bulk/helpers/cron_job/thread_job.py
telus_bulk/helpers/web_methods/__init__.py
telus_bulk/helpers/web_methods/async_web_methods_helper.py
telus_bulk/helpers/web_methods/web_methods_helper.py
telus_bulk/models/__init__.py
telus_bulk/models/product_type.py
telus_bulk/models/ams/__init__.py
telus_bulk/models/ams/address_detail_model.py
telus_bulk/models/ams/city_alias.py
telus_bulk/models/ams/coordinate.py
telus_bulk/models/ams/credentials_response.py
telus_bulk/models/ams/e911_address.py
telus_bulk/models/ams/fms_address.py
telus_bulk/models/ams/reference_id.py
telus_bulk/models/ams/reference_ids.py
telus_bulk/models/ams/zone_attribute.py
telus_bulk/models/ams/zone_info_item.py
telus_bulk/models/available_partners/__init__.py
telus_bulk/models/available_partners/partners_enum.py
telus_bulk/models/clli/__init__.py
telus_bulk/models/clli/clli_dto.py
telus_bulk/models/firestore/firestore_reference.py
telus_bulk/models/reports/__init__.py
telus_bulk/models/reports/report_address.py
telus_bulk/models/reports/report_qualification_detail.py
telus_bulk/models/tmf_620/__init__.py
telus_bulk/models/tmf_620/status_enum.py
telus_bulk/models/tmf_645/__init__.py
telus_bulk/models/tmf_645/addressable.py
telus_bulk/models/tmf_645/alternate_service_proposal.py
telus_bulk/models/tmf_645/characteristic.py
telus_bulk/models/tmf_645/characteristic_relationship.py
telus_bulk/models/tmf_645/check_service_qualification.py
telus_bulk/models/tmf_645/check_service_qualification_attribute_value_change_event.py
telus_bulk/models/tmf_645/check_service_qualification_attribute_value_change_event_payload.py
telus_bulk/models/tmf_645/check_service_qualification_create.py
telus_bulk/models/tmf_645/check_service_qualification_create_event.py
telus_bulk/models/tmf_645/check_service_qualification_create_event_payload.py
telus_bulk/models/tmf_645/check_service_qualification_delete_event.py
telus_bulk-1.3.7.dist-info/LICENSE
telus_bulk-1.3.7.dist-info/METADATA
telus_bulk-1.3.7.dist-info/WHEEL
telus_bulk-1.3.7.dist-info/top_level.txt
telus_bulk-1.3.7.dist-info/RECORD
