Metadata-Version: 2.1
Name: telus-bulk
Version: 1.3.7
Summary: A package to be used to store classes used among Telus Bulk repositories of TMF-645, TMF-620 and AMS models
Author-email: Jose Olmedo <jose.olmedo@telusinternational.com>
License: Copyright (c) 2018 The Python Packaging Authority
Project-URL: Homepage, https://github.com/telus/telus-bulk-types-pypi
Project-URL: Bug Tracker, https://github.com/telus/telus-bulk-types-pypi/issues
Classifier: Programming Language :: Python :: 3
Classifier: License :: OSI Approved :: MIT License
Classifier: Operating System :: OS Independent
Requires-Python: >=3.10.7
License-File: LICENSE
